[
  {
    "Year":2005,
    "Collisions":669
  },
  {
    "Year":2006,
    "Collisions":677
  },
  {
    "Year":2007,
    "Collisions":677
  },
  {
    "Year":2008,
    "Collisions":646
  },
  {
    "Year":2009,
    "Collisions":549
  },
  {
    "Year":2010,
    "Collisions":550
  },
  {
    "Year":2011,
    "Collisions":471
  },
  {
    "Year":2012,
    "Collisions":695
  },
  {
    "Year":2013,
    "Collisions":565
  },
  {
    "Year":2014,
    "Collisions":621
  },
  {
    "Year":2015,
    "Collisions":536
  },
  {
    "Year":2016,
    "Collisions":402
  },
  {
    "Year":2017,
    "Collisions":389
  }
]