[
  {
    "Date Taken":"31/03/2014",
    "Less than 1":306,
    "1":328,
    "2":332,
    "3":312,
    "4":308,
    "5":317,
    "6":274,
    "7":321,
    "8":273,
    "9":295,
    "10":320,
    "11":273,
    "12":293,
    "13":324,
    "14":335,
    "15":294,
    "16":348,
    "17":343,
    "18":343,
    "19":354,
    "20":373,
    "21":398,
    "22":407,
    "23":447,
    "24":393,
    "25":397,
    "26":395,
    "27":396,
    "28":343,
    "29":395,
    "30":373,
    "31":391,
    "32":392,
    "33":396,
    "34":384,
    "35":353,
    "36":368,
    "37":381,
    "38":383,
    "39":414,
    "40":408,
    "41":457,
    "42":460,
    "43":486,
    "44":521,
    "45":501,
    "46":521,
    "47":533,
    "48":502,
    "49":488,
    "50":506,
    "51":510,
    "52":493,
    "53":477,
    "54":473,
    "55":463,
    "56":452,
    "57":422,
    "58":366,
    "59":356,
    "60":387,
    "61":401,
    "62":372,
    "63":378,
    "64":406,
    "65":405,
    "66":382,
    "67":468,
    "68":306,
    "69":291,
    "70":296,
    "71":233,
    "72":215,
    "73":246,
    "74":256,
    "75":264,
    "76":239,
    "77":243,
    "78":215,
    "79":210,
    "80":213,
    "81":194,
    "82":182,
    "83":188,
    "84":162,
    "85":164,
    "86":134,
    "87":156,
    "88":113,
    "89":105,
    "90":87,
    "91":60,
    "92":71,
    "93":69,
    "94":47,
    "95 and over":92
  }
]